nakametpy/__init__.py
nakametpy/_error.py
nakametpy/_version.py
nakametpy/aviation.py
nakametpy/bufr.py
nakametpy/cmaps.py
nakametpy/constants.py
nakametpy/grads.py
nakametpy/jma.py
nakametpy/kinematics.py
nakametpy/thermo.py
nakametpy/util.py
nakametpy/data/nws/README.md
nakametpy/data/nws/stations.json
nakametpy/product/__init__.py
nakametpy/product/liden.py
nakametpy/product/synop1min.py
nakametpy/tables/__init__.py
nakametpy/tables/bufrtab.CodeFlag_ADD_1_0
nakametpy/tables/bufrtab.CodeFlag_LOC_0_7_1
nakametpy/tables/bufrtab.CodeFlag_STD_0_13
nakametpy/tables/bufrtab.CodeFlag_STD_0_14
nakametpy/tables/bufrtab.CodeFlag_STD_0_15
nakametpy/tables/bufrtab.CodeFlag_STD_0_16
nakametpy/tables/bufrtab.CodeFlag_STD_0_17
nakametpy/tables/bufrtab.CodeFlag_STD_0_18
nakametpy/tables/bufrtab.CodeFlag_STD_0_19
nakametpy/tables/bufrtab.CodeFlag_STD_0_20
nakametpy/tables/bufrtab.CodeFlag_STD_0_21
nakametpy/tables/bufrtab.CodeFlag_STD_0_22
nakametpy/tables/bufrtab.CodeFlag_STD_0_23
nakametpy/tables/bufrtab.CodeFlag_STD_0_24
nakametpy/tables/bufrtab.CodeFlag_STD_0_25
nakametpy/tables/bufrtab.CodeFlag_STD_0_26
nakametpy/tables/bufrtab.CodeFlag_STD_0_27
nakametpy/tables/bufrtab.CodeFlag_STD_0_28
nakametpy/tables/bufrtab.CodeFlag_STD_0_29
nakametpy/tables/bufrtab.CodeFlag_STD_0_30
nakametpy/tables/bufrtab.CodeFlag_STD_0_31
nakametpy/tables/bufrtab.CodeFlag_STD_0_32
nakametpy/tables/bufrtab.CodeFlag_STD_0_33
nakametpy/tables/bufrtab.CodeFlag_STD_0_34
nakametpy/tables/bufrtab.CodeFlag_STD_0_35
nakametpy/tables/bufrtab.CodeFlag_STD_0_36
nakametpy/tables/bufrtab.CodeFlag_STD_0_37
nakametpy/tables/bufrtab.CodeFlag_STD_0_38
nakametpy/tables/bufrtab.CodeFlag_STD_0_39
nakametpy/tables/bufrtab.CodeFlag_STD_0_40
nakametpy/tables/bufrtab.CodeFlag_STD_0_41
nakametpy/tables/bufrtab.CodeFlag_STD_0_42
nakametpy/tables/bufrtab.CodeFlag_STD_0_43
nakametpy/tables/bufrtab.CodeFlag_STD_0_44
nakametpy/tables/bufrtab.TableB_ADD_1_0
nakametpy/tables/bufrtab.TableB_LOC_0_7_1
nakametpy-2026.1.0.dist-info/LICENSE
nakametpy-2026.1.0.dist-info/METADATA
nakametpy-2026.1.0.dist-info/WHEEL
nakametpy-2026.1.0.dist-info/top_level.txt
nakametpy-2026.1.0.dist-info/RECORD
