Metadata-Version: 2.1
Name: nakametpy
Version: 2026.1.0
Summary: Meteorological modules for calculation and colormap.
Home-page: https://github.com/muchojp/NakaMetPy
Author: muchojp
Author-email: contact.muchiwo@gmail.com
License: BSD 3-clause
Requires-Python: >=3.7.0
License-File: LICENSE
Requires-Dist: numpy
Requires-Dist: matplotlib
Requires-Dist: pandas
Requires-Dist: pillow
